newstryletter/__init__.py
newstryletter/admin.py
newstryletter/apps.py
newstryletter/decorators.py
newstryletter/forms.py
newstryletter/migrations/0001_initial.py
newstryletter/migrations/0002_newsletter.py
newstryletter/migrations/0003_rename_craeted_at_newsletter_created_at.py
newstryletter/migrations/__init__.py
newstryletter/models.py
newstryletter/settings.py
newstryletter/templates/newsletter/index.html
newstryletter/tests.py
newstryletter/urls.py
newstryletter/views.py
newstryletter-0.4.2.dist-info/METADATA
newstryletter-0.4.2.dist-info/WHEEL
newstryletter-0.4.2.dist-info/RECORD
